uyaml/__init__.py
uyaml/file.py
uyaml/loader.py
uyaml/type.py
uyaml-0.0.7.dist-info/AUTHORS.md
uyaml-0.0.7.dist-info/LICENSE.md
uyaml-0.0.7.dist-info/METADATA
uyaml-0.0.7.dist-info/WHEEL
uyaml-0.0.7.dist-info/top_level.txt
uyaml-0.0.7.dist-info/RECORD
