Metadata-Version: 2.1
Name: uyaml
Version: 0.0.7
Summary: Provides user-friendly interface for YAML data stream serialization with OOP support.
Home-page: https://github.com/vyahello/uyaml
Author: Volodymyr Yahello
Author-email: vyahello@gmail.com
License: UNKNOWN
Platform: UNKNOWN
Classifier: Programming Language :: Python :: 3.6
Classifier: Programming Language :: Python :: 3.7
Classifier: Programming Language :: Python :: 3.8
Classifier: License :: OSI Approved :: MIT License
Classifier: Operating System :: OS Independent
Requires-Python: >=3.6
Requires-Dist: pyyaml (==5.3.1)
Requires-Dist: dataclasses (==0.6.0)
Requires-Dist: enforce-pep8 (==0.0.11)
